sphinxcontrib_hdl_diagrams/__init__.py
sphinxcontrib_hdl_diagrams/version.py
sphinxcontrib_hdl_diagrams-0.0.post160.dist-info/AUTHORS
sphinxcontrib_hdl_diagrams-0.0.post160.dist-info/LICENSE
sphinxcontrib_hdl_diagrams-0.0.post160.dist-info/METADATA
sphinxcontrib_hdl_diagrams-0.0.post160.dist-info/WHEEL
sphinxcontrib_hdl_diagrams-0.0.post160.dist-info/top_level.txt
sphinxcontrib_hdl_diagrams-0.0.post160.dist-info/RECORD
