Metadata-Version: 2.1
Name: sphinxcontrib-hdl-diagrams
Version: 0.0.post160
Summary: Generate diagrams from HDL in Sphinx.
Home-page: https://github.com/SymbiFlow/sphinxcontrib-hdl-diagrams
Author: SymbiFlow Authors
Author-email: symbiflow@lists.librecores.org
License: Apache 2.0
Keywords: Verilog nMigen RTLIL yosys HDL sphinx sphinx-extension netlistsvg FPGA
Classifier: Development Status :: 4 - Beta
Classifier: Framework :: Sphinx :: Extension
Classifier: Intended Audience :: Developers
Classifier: License :: OSI Approved :: Apache Software License
Classifier: Natural Language :: English
Classifier: Programming Language :: Python :: 3.5
Classifier: Programming Language :: Python :: 3.6
Classifier: Topic :: Text Processing
License-File: LICENSE
License-File: AUTHORS
Requires-Dist: setuptools
Requires-Dist: docutils
Requires-Dist: sphinx
Requires-Dist: nmigen
Requires-Dist: yowasp-yosys
